obsidian_base_logger/__init__.py
obsidian_base_logger/__main__.py
obsidian_base_logger/cli.py
obsidian_base_logger/executor.py
obsidian_base_logger/formatter.py
obsidian_base_logger/utils.py
obsidian_base_logger-0.1.0.dist-info/METADATA
obsidian_base_logger-0.1.0.dist-info/WHEEL
obsidian_base_logger-0.1.0.dist-info/entry_points.txt
obsidian_base_logger-0.1.0.dist-info/RECORD
