Metadata-Version: 2.4
Name: obsidian-base-logger
Version: 0.1.0
Summary: A CLI tool that wraps shell processes and logs execution metadata to Obsidian-compatible Markdown files
Author: obsidian-base-logger contributors
Requires-Python: >=3.10
Requires-Dist: psutil>=5.9.0
